hardware/fpga/ring_oscillator.v
`timescale 1ns / 1ps

module ring_oscillator #(
    parameter DELAY = 1 // Default delay is 1ns
)(
    input wire enable,
    output wire osc_out
);

    wire w1, w2, w3;

    // The NAND gate enables/disables the loop
    nand #DELAY gate1 (w1, enable, w3);

    // Inverters with configurable delay
    // This simulates manufacturing differences
    not #DELAY gate2 (w2, w1);
    not #DELAY gate3 (w3, w2);

    assign osc_out = w3;

endmodule

hardware/fpga/trng.v
`timescale 1ns / 1ps

module trng (
    input wire clk,
    input wire rst,
    output reg [15:0] rand_out
);

    wire ro1_out, ro2_out, ro3_out, ro4_out;

    // Instantiate with DIFFERENT delays to force desynchronization
    // These specific numbers (2, 3, 5, 7) are prime, which helps chaos.
    ring_oscillator #(.DELAY(2)) ro1 (.enable(!rst), .osc_out(ro1_out));
    ring_oscillator #(.DELAY(3)) ro2 (.enable(!rst), .osc_out(ro2_out));
    ring_oscillator #(.DELAY(5)) ro3 (.enable(!rst), .osc_out(ro3_out));
    ring_oscillator #(.DELAY(7)) ro4 (.enable(!rst), .osc_out(ro4_out));

    wire raw_entropy;
    assign raw_entropy = ro1_out ^ ro2_out ^ ro3_out ^ ro4_out;

    // Shift Register Accumulator
    always @(posedge clk or posedge rst) begin
        if (rst) begin
            rand_out <= 16'b0;
        end else begin
            rand_out <= {rand_out[14:0], raw_entropy};
        end
    end

endmodule

hardware/rtl/spu_core.v
`default_nettype none

module spu_core #(
    parameter DATA_WIDTH     = 16,
    parameter FRAC_BITS      = 12,
    parameter NEIGHBOR_COUNT = 4
)(
    input wire                      clk,
    input wire                      rst_n,
    input wire signed [DATA_WIDTH-1:0]  h_local_field,
    
    // Flattened array ports
    input wire signed [DATA_WIDTH-1:0]  j_coupling_0,
    input wire signed [DATA_WIDTH-1:0]  j_coupling_1,
    input wire signed [DATA_WIDTH-1:0]  j_coupling_2,
    input wire signed [DATA_WIDTH-1:0]  j_coupling_3,
    
    input wire signed [1:0]             neighbor_spin_0,
    input wire signed [1:0]             neighbor_spin_1,
    input wire signed [1:0]             neighbor_spin_2,
    input wire signed [1:0]             neighbor_spin_3,

    input wire        [DATA_WIDTH-1:0]  temperature,
    // REMOVED: input wire [DATA_WIDTH-1:0] rand_num, 
    // We now generate this internally!
    
    output reg signed [1:0]             current_spin_state
);

    localparam FULL_WIDTH = DATA_WIDTH + $clog2(NEIGHBOR_COUNT);

    // --- INTERNAL TRNG INSTANTIATION ---
    wire [15:0] internal_rand_num;
    
    // We instantiate the TRNG we just built.
    // !rst_n because our system uses active-low reset (rst_n), 
    // but our TRNG used active-high (rst).
    trng entropy_source (
        .clk(clk),
        .rst(!rst_n), 
        .rand_out(internal_rand_num)
    );
    // -----------------------------------

    integer i;

    // Internal arrays for cleaner logic
    wire signed [DATA_WIDTH-1:0] j_couplings [0:NEIGHBOR_COUNT-1];
    wire signed [1:0]            neighbor_spins [0:NEIGHBOR_COUNT-1];

    assign j_couplings[0] = j_coupling_0;
    assign j_couplings[1] = j_coupling_1;
    assign j_couplings[2] = j_coupling_2;
    assign j_couplings[3] = j_coupling_3;

    assign neighbor_spins[0] = neighbor_spin_0;
    assign neighbor_spins[1] = neighbor_spin_1;
    assign neighbor_spins[2] = neighbor_spin_2;
    assign neighbor_spins[3] = neighbor_spin_3;

    reg  signed [FULL_WIDTH-1:0]   coupling_energy_sum;
    reg  signed [FULL_WIDTH-1:0]   total_local_energy;
    wire signed [FULL_WIDTH-1:0]   delta_energy;
    wire                           accept_flip;
    wire signed [FULL_WIDTH-1:0]   scaled_temperature;

    always @(*) begin
        coupling_energy_sum = 0;
        for (i = 0; i < NEIGHBOR_COUNT; i = i + 1) begin
            coupling_energy_sum = coupling_energy_sum + (j_couplings[i] * neighbor_spins[i]);
        end
    end

    always @(*) begin
        total_local_energy = coupling_energy_sum + (h_local_field <<< $clog2(NEIGHBOR_COUNT));
    end

    assign delta_energy = (total_local_energy <<< 1) * current_spin_state;
    assign scaled_temperature = temperature <<< $clog2(NEIGHBOR_COUNT);
    
    // Logic: If Delta E < 0, always flip.
    // If Delta E > 0, flip with probability exp(-Delta E / T).
    // We compare internal_rand_num against the threshold.
    assign accept_flip = (delta_energy < 0) || (internal_rand_num < (1'b1 << FRAC_BITS) - (delta_energy / (scaled_temperature + 1)));

    always @(posedge clk or negedge rst_n) begin
        if (!rst_n) begin
            current_spin_state <= 2'b01; // +1
        end else begin
            if (accept_flip) begin
                current_spin_state <= -current_spin_state;
            end
        end
    end

endmodule
`default_nettype wire

hardware/fpga/tb_spu_core.v
`timescale 1ns / 1ps
`include "ring_oscillator.v"
`include "trng.v"
`include "spu_core.v"

module tb_spu_core;
    reg clk, rst_n;
    // Dummy inputs for physics
    reg signed [15:0] h, j0, j1, j2, j3, temp;
    reg signed [1:0] s0, s1, s2, s3;
    wire signed [1:0] out_spin;

    spu_core uut (
        .clk(clk), .rst_n(rst_n),
        .h_local_field(h),
        .j_coupling_0(j0), .j_coupling_1(j1), .j_coupling_2(j2), .j_coupling_3(j3),
        .neighbor_spin_0(s0), .neighbor_spin_1(s1), .neighbor_spin_2(s2), .neighbor_spin_3(s3),
        .temperature(temp),
        .current_spin_state(out_spin)
    );

    initial begin
        clk=0; 
        forever #5 clk=~clk;
    end

    initial begin
        $dumpfile("spu_core_test.vcd");
        $dumpvars(0, tb_spu_core);
        
        rst_n = 0; #20; rst_n = 1;

        // Set parameters to encourage flipping
        h = 0; 
        j0=0; j1=0; j2=0; j3=0;
        s0=1; s1=1; s2=1; s3=1;
        temp = 16'd1000; // High temp = high randomness

        #5000;
        $finish;
    end
endmodule

hardware/fpga/spu_core_test.vcd
$date
	Thu Dec 25 18:55:49 2025
$end
$version
	Icarus Verilog
$end
$timescale
	1ps
$end
$scope module tb_spu_core $end
$var wire 2 ! out_spin [1:0] $end
$var reg 1 " clk $end
$var reg 16 # h [15:0] $end
$var reg 16 $ j0 [15:0] $end
$var reg 16 % j1 [15:0] $end
$var reg 16 & j2 [15:0] $end
$var reg 16 ' j3 [15:0] $end
$var reg 1 ( rst_n $end
$var reg 2 ) s0 [1:0] $end
$var reg 2 * s1 [1:0] $end
$var reg 2 + s2 [1:0] $end
$var reg 2 , s3 [1:0] $end
$var reg 16 - temp [15:0] $end
$scope module uut $end
$var wire 1 . accept_flip $end
$var wire 1 " clk $end
$var wire 16 / h_local_field [15:0] $end
$var wire 16 0 j_coupling_0 [15:0] $end
$var wire 16 1 j_coupling_1 [15:0] $end
$var wire 16 2 j_coupling_2 [15:0] $end
$var wire 16 3 j_coupling_3 [15:0] $end
$var wire 2 4 neighbor_spin_0 [1:0] $end
$var wire 2 5 neighbor_spin_1 [1:0] $end
$var wire 2 6 neighbor_spin_2 [1:0] $end
$var wire 2 7 neighbor_spin_3 [1:0] $end
$var wire 1 ( rst_n $end
$var wire 16 8 temperature [15:0] $end
$var wire 18 9 scaled_temperature [17:0] $end
$var wire 16 : internal_rand_num [15:0] $end
$var wire 18 ; delta_energy [17:0] $end
$var parameter 32 < DATA_WIDTH $end
$var parameter 32 = FRAC_BITS $end
$var parameter 33 > FULL_WIDTH $end
$var parameter 32 ? NEIGHBOR_COUNT $end
$var reg 18 @ coupling_energy_sum [17:0] $end
$var reg 2 A current_spin_state [1:0] $end
$var reg 18 B total_local_energy [17:0] $end
$var integer 32 C i [31:0] $end
$scope module entropy_source $end
$var wire 1 " clk $end
$var wire 1 D raw_entropy $end
$var wire 1 E rst $end
$var wire 1 F ro4_out $end
$var wire 1 G ro3_out $end
$var wire 1 H ro2_out $end
$var wire 1 I ro1_out $end
$var reg 16 J rand_out [15:0] $end
$scope module ro1 $end
$var wire 1 K enable $end
$var wire 1 I osc_out $end
$var wire 1 L w1 $end
$var wire 1 M w2 $end
$var wire 1 N w3 $end
$var parameter 32 O DELAY $end
$upscope $end
$scope module ro2 $end
$var wire 1 P enable $end
$var wire 1 H osc_out $end
$var wire 1 Q w1 $end
$var wire 1 R w2 $end
$var wire 1 S w3 $end
$var parameter 32 T DELAY $end
$upscope $end
$scope module ro3 $end
$var wire 1 U enable $end
$var wire 1 G osc_out $end
$var wire 1 V w1 $end
$var wire 1 W w2 $end
$var wire 1 X w3 $end
$var parameter 32 Y DELAY $end
$upscope $end
$scope module ro4 $end
$var wire 1 Z enable $end
$var wire 1 F osc_out $end
$var wire 1 [ w1 $end
$var wire 1 \ w2 $end
$var wire 1 ] w3 $end
$var parameter 32 ^ DELAY $end
$upscope $end
$upscope $end
$upscope $end
$upscope $end
$enddefinitions $end
$comment Show the parameter values. $end
$dumpall
b111 ^
b101 Y
b11 T
b10 O
b100 ?
b10010 >
b1100 =
b10000 <
$end
#0
$dumpvars
x]
x\
x[
0Z
xX
xW
xV
0U
xS
xR
xQ
0P
xN
xM
xL
0K
b0 J
xI
xH
xG
xF
1E
xD
bx C
bx B
b1 A
bx @
bx ;
b0 :
bx00 9
bx 8
bx 7
bx 6
bx 5
bx 4
bx 3
bx 2
bx 1
bx 0
bx /
x.
bx -
bx ,
bx +
bx *
bx )
0(
bx '
bx &
bx %
bx $
bx #
0"
b1 !
$end
#2000
1L
#3000
1Q
#4000
0M
#5000
1V
1"
#6000
1I
1N
0R
#7000
1[
#9000
1H
1S
#10000
0W
0"
#14000
0\
#15000
1G
1X
1"
#20000
1.
b0 ;
b0 B
b111110100000 9
b100 C
b0 @
0"
b1111101000 -
b1111101000 8
b1 ,
b1 7
b1 +
b1 6
b1 *
b1 5
b1 )
b1 4
b0 '
b0 3
b0 &
b0 2
b0 %
b0 1
b0 $
b0 0
b0 #
b0 /
1K
1P
1U
1Z
0E
1(
#21000
0D
1F
1]
#22000
0L
#23000
0Q
#24000
1M
#25000
b11 !
b11 A
0V
1"
#26000
1D
0I
0N
1R
#28000
1L
0[
#29000
0D
0H
0S
#30000
0M
1W
0"
#32000
1D
1I
1N
1Q
#34000
0L
#35000
b1 :
b1 J
b1 !
b1 A
0D
0R
0G
0X
1"
1\
#36000
1M
#38000
0I
0N
1H
1S
#40000
1L
1V
0"
#41000
0Q
#42000
1D
0M
0F
0]
#44000
0D
1I
1N
1R
#45000
b10 :
b10 J
b11 !
b11 A
0W
1"
#46000
0L
#47000
1D
0H
0S
#48000
1M
#49000
1[
#50000
1D
0I
0N
1Q
1G
1X
0"
#52000
1L
#53000
0R
#54000
0M
#55000
b101 :
b101 J
b1 !
b1 A
0V
1"
#56000
1I
1N
1H
1S
0\
#58000
0L
#59000
0Q
#60000
1M
1W
0"
#62000
0D
0I
0N
1R
#63000
1D
1F
1]
#64000
1L
#65000
b1011 :
b1011 J
b11 !
b11 A
1D
0H
0S
0G
0X
1"
#66000
0M
#68000
0D
1I
1N
1Q
#70000
0L
1V
0"
0[
#71000
0R
#72000
1M
#74000
0I
0N
1H
1S
#75000
b10110 :
b10110 J
b1 !
b1 A
0W
1"
#76000
1L
#77000
0Q
1\
#78000
0M
#80000
0D
1I
1N
1R
1G
1X
0"
#82000
0L
#83000
1D
0H
0S
#84000
0D
1M
0F
0]
#85000
b101100 :
b101100 J
b11 !
b11 A
0V
1"
#86000
1D
0I
0N
1Q
#88000
1L
#89000
0R
#90000
0M
1W
0"
#91000
1[
#92000
1I
1N
1H
1S
#94000
0L
#95000
b1011001 :
b1011001 J
b1 !
b1 A
0D
0Q
0G
0X
1"
#96000
1M
#98000
1D
0I
0N
1R
0\
#100000
1L
1V
0"
#101000
0D
0H
0S
#102000
0M
#104000
1D
1I
1N
1Q
#105000
b10110010 :
b10110010 J
b11 !
b11 A
0D
0W
1"
1F
1]
#106000
0L
#107000
0R
#108000
1M
#110000
1D
0I
0N
1H
1S
1G
1X
0"
#112000
1L
0[
#113000
0Q
#114000
0M
#115000
b101100101 :
b101100101 J
b1 !
b1 A
0V
1"
#116000
0D
1I
1N
1R
#118000
0L
#119000
1D
0H
0S
1\
#120000
1M
1W
0"
#122000
0D
0I
0N
1Q
#124000
1L
#125000
b1011001010 :
b1011001010 J
b11 !
b11 A
1D
0R
0G
0X
1"
#126000
0D
0M
0F
0]
#128000
1I
1N
1H
1S
#130000
0L
1V
0"
#131000
0Q
#132000
1M
#133000
1[
#134000
1D
0I
0N
1R
#135000
b10110010101 :
b10110010101 J
b1 !
b1 A
0W
1"
#136000
1L
#137000
0D
0H
0S
#138000
0M
#140000
0D
1I
1N
1Q
1G
1X
0"
0\
#142000
0L
#143000
0R
#144000
1M
#145000
b101100101010 :
b101100101010 J
b11 !
b11 A
0V
1"
#146000
0I
0N
1H
1S
#147000
1D
1F
1]
#148000
1L
#149000
0Q
#150000
0M
1W
0"
#152000
0D
1I
1N
1R
#154000
0L
0[
#155000
0.
b1011001010100 :
b1011001010100 J
b1 !
b1 A
0D
0H
0S
0G
0X
1"
#156000
1M
#158000
1D
0I
0N
1Q
#160000
1L
1V
0"
#161000
0R
1\
#162000
0M
#164000
1I
1N
1H
1S
#165000
b10110010101001 :
b10110010101001 J
0W
1"
#166000
0L
#167000
0Q
#168000
0D
1M
0F
0]
#170000
0D
0I
0N
1R
1G
1X
0"
#172000
1L
#173000
1D
0H
0S
#174000
0M
#175000
b101100101010011 :
b101100101010011 J
0V
1"
1[
#176000
0D
1I
1N
1Q
#178000
0L
#179000
0R
#180000
1M
1W
0"
#182000
0I
0N
1H
1S
0\
#184000
1L
#185000
b1011001010100110 :
b1011001010100110 J
1D
0Q
0G
0X
1"
#186000
0M
#188000
0D
1I
1N
1R
#189000
1D
1F
1]
#190000
0L
1V
0"
#191000
0D
0H
0S
#192000
1M
#194000
1D
0I
0N
1Q
#195000
b110010101001101 :
b110010101001101 J
0W
1"
#196000
1L
0[
#197000
0R
#198000
0M
#200000
0D
1I
1N
1H
1S
1G
1X
0"
#202000
0L
#203000
0Q
1\
#204000
1M
#205000
b1100101010011010 :
b1100101010011010 J
0V
1"
#206000
1D
0I
0N
1R
#208000
1L
#209000
0D
0H
0S
#210000
1D
0M
1W
0"
0F
0]
#212000
0D
1I
1N
1Q
#214000
0L
#215000
b1001010100110100 :
b1001010100110100 J
1D
0R
0G
0X
1"
#216000
1M
#217000
1[
#218000
0I
0N
1H
1S
#220000
1L
1V
0"
#221000
0Q
#222000
0M
#224000
0D
1I
1N
1R
0\
#225000
b10101001101000 :
b10101001101000 J
0W
1"
#226000
0L
#227000
1D
0H
0S
#228000
1M
#230000
1D
0I
0N
1Q
1G
1X
0"
#231000
0D
1F
1]
#232000
1L
#233000
0R
#234000
0M
#235000
b101010011010000 :
b101010011010000 J
0V
1"
#236000
1I
1N
1H
1S
#238000
0L
0[
#239000
0Q
#240000
1M
1W
0"
#242000
1D
0I
0N
1R
#244000
1L
#245000
b1010100110100001 :
b1010100110100001 J
1D
0H
0S
0G
0X
1"
1\
#246000
0M
#248000
0D
1I
1N
1Q
#250000
0L
1V
0"
#251000
0R
#252000
1D
1M
0F
0]
#254000
0I
0N
1H
1S
#255000
b101001101000011 :
b101001101000011 J
0W
1"
#256000
1L
#257000
0Q
#258000
0M
#259000
1[
#260000
1D
1I
1N
1R
1G
1X
0"
#262000
0L
#263000
0D
0H
0S
#264000
1M
#265000
b1010011010000110 :
b1010011010000110 J
0V
1"
#266000
1D
0I
0N
1Q
0\
#268000
1L
#269000
0R
#270000
0M
1W
0"
#272000
1I
1N
1H
1S
#273000
0D
1F
1]
#274000
0L
#275000
b100110100001100 :
b100110100001100 J
1D
0Q
0G
0X
1"
#276000
1M
#278000
0D
0I
0N
1R
#280000
1L
1V
0"
0[
#281000
1D
0H
0S
#282000
0M
#284000
0D
1I
1N
1Q
#285000
b1001101000011000 :
b1001101000011000 J
0W
1"
#286000
0L
#287000
0R
1\
#288000
1M
#290000
1D
0I
0N
1H
1S
1G
1X
0"
#292000
1L
#293000
0Q
#294000
0D
0M
0F
0]
#295000
b11010000110000 :
b11010000110000 J
0V
1"
#296000
1D
1I
1N
1R
#298000
0L
#299000
0D
0H
0S
#300000
1M
1W
0"
#301000
1[
#302000
1D
0I
0N
1Q
#304000
1L
#305000
b110100001100001 :
b110100001100001 J
0D
0R
0G
0X
1"
#306000
0M
#308000
1I
1N
1H
1S
0\
#310000
0L
1V
0"
#311000
0Q
#312000
1M
#314000
1D
0I
0N
1R
#315000
b1101000011000010 :
b1101000011000010 J
0D
0W
1"
1F
1]
#316000
1L
#317000
1D
0H
0S
#318000
0M
#320000
1D
1I
1N
1Q
1G
1X
0"
#322000
0L
0[
#323000
0R
#324000
1M
#325000
b1010000110000101 :
b1010000110000101 J
0V
1"
#326000
0I
0N
1H
1S
#328000
1L
#329000
0Q
1\
#330000
0M
1W
0"
#332000
0D
1I
1N
1R
#334000
0L
#335000
b100001100001010 :
b100001100001010 J
0D
0H
0S
0G
0X
1"
#336000
1D
1M
0F
0]
#338000
0D
0I
0N
1Q
#340000
1L
1V
0"
#341000
0R
#342000
0M
#343000
1[
#344000
1I
1N
1H
1S
#345000
b1000011000010100 :
b1000011000010100 J
0W
1"
#346000
0L
#347000
0Q
#348000
1M
#350000
0D
0I
0N
1R
1G
1X
0"
0\
#352000
1L
#353000
1D
0H
0S
#354000
0M
#355000
1.
b110000101001 :
b110000101001 J
0V
1"
#356000
0D
1I
1N
1Q
#357000
1D
1F
1]
#358000
0L
#359000
0R
#360000
1M
1W
0"
#362000
0I
0N
1H
1S
#364000
1L
0[
#365000
0.
b1100001010011 :
b1100001010011 J
b11 !
b11 A
0D
0Q
0G
0X
1"
#366000
0M
#368000
1D
1I
1N
1R
#370000
0L
1V
0"
#371000
0D
0H
0S
1\
#372000
1M
#374000
1D
0I
0N
1Q
#375000
b11000010100111 :
b11000010100111 J
0W
1"
#376000
1L
#377000
0R
#378000
0D
0M
0F
0]
#380000
1D
1I
1N
1H
1S
1G
1X
0"
#382000
0L
#383000
0Q
#384000
1M
#385000
b110000101001111 :
b110000101001111 J
0V
1"
1[
#386000
0D
0I
0N
1R
#388000
1L
#389000
1D
0H
0S
#390000
0M
1W
0"
#392000
0D
1I
1N
1Q
0\
#394000
0L
#395000
b1100001010011110 :
b1100001010011110 J
1D
0R
0G
0X
1"
#396000
1M
#398000
0I
0N
1H
1S
#399000
0D
1F
1]
#400000
1L
1V
0"
#401000
0Q
#402000
0M
#404000
1D
1I
1N
1R
#405000
b1000010100111101 :
b1000010100111101 J
0W
1"
#406000
0L
0[
#407000
0D
0H
0S
#408000
1M
#410000
0D
0I
0N
1Q
1G
1X
0"
#412000
1L
#413000
0R
1\
#414000
0M
#415000
1.
b101001111010 :
b101001111010 J
0V
1"
#416000
1I
1N
1H
1S
#418000
0L
#419000
0Q
#420000
1D
1M
1W
0"
0F
0]
#422000
0D
0I
0N
1R
#424000
1L
#425000
0.
b1010011110100 :
b1010011110100 J
b1 !
b1 A
0D
0H
0S
0G
0X
1"
#426000
0M
#427000
1[
#428000
1D
1I
1N
1Q
#430000
0L
1V
0"
#431000
0R
#432000
1M
#434000
0I
0N
1H
1S
0\
#435000
b10100111101001 :
b10100111101001 J
0W
1"
#436000
1L
#437000
0Q
#438000
0M
#440000
1D
1I
1N
1R
1G
1X
0"
#441000
0D
1F
1]
#442000
0L
#443000
1D
0H
0S
#444000
1M
#445000
b101001111010011 :
b101001111010011 J
0V
1"
#446000
0D
0I
0N
1Q
#448000
1L
0[
#449000
0R
#450000
0M
1W
0"
#452000
1I
1N
1H
1S
#454000
0L
#455000
b1010011110100110 :
b1010011110100110 J
1D
0Q
0G
0X
1"
1\
#456000
1M
#458000
0D
0I
0N
1R
#460000
1L
1V
0"
#461000
1D
0H
0S
#462000
0D
0M
0F
0]
#464000
1D
1I
1N
1Q
#465000
b100111101001101 :
b100111101001101 J
0W
1"
#466000
0L
#467000
0R
#468000
1M
#469000
1[
#470000
0D
0I
0N
1H
1S
1G
1X
0"
#472000
1L
#473000
0Q
#474000
0M
#475000
b1001111010011010 :
b1001111010011010 J
0V
1"
#476000
1D
1I
1N
1R
0\
#478000
0L
#479000
0D
0H
0S
#480000
1M
1W
0"
#482000
1D
0I
0N
1Q
#483000
0D
1F
1]
#484000
1L
#485000
b11110100110100 :
b11110100110100 J
1D
0R
0G
0X
1"
#486000
0M
#488000
1I
1N
1H
1S
#490000
0L
1V
0"
0[
#491000
0Q
#492000
1M
#494000
0D
0I
0N
1R
#495000
b111101001101000 :
b111101001101000 J
0W
1"
#496000
1L
#497000
1D
0H
0S
1\
#498000
0M
#500000
1D
1I
1N
1Q
1G
1X
0"
#502000
0L
#503000
0R
#504000
0D
1M
0F
0]
#505000
b1111010011010000 :
b1111010011010000 J
0V
1"
#506000
0I
0N
1H
1S
#508000
1L
#509000
0Q
#510000
0M
1W
0"
#511000
1[
#512000
1D
1I
1N
1R
#514000
0L
#515000
b1110100110100001 :
b1110100110100001 J
1D
0H
0S
0G
0X
1"
#516000
1M
#518000
0D
0I
0N
1Q
0\
#520000
1L
1V
0"
#521000
0R
#522000
0M
#524000
1I
1N
1H
1S
#525000
b1101001101000011 :
b1101001101000011 J
1D
0W
1"
1F
1]
#526000
0L
#527000
0Q
#528000
1M
#530000
1D
0I
0N
1R
1G
1X
0"
#532000
1L
0[
#533000
0D
0H
0S
#534000
0M
#535000
b1010011010000110 :
b1010011010000110 J
0V
1"
#536000
1D
1I
1N
1Q
#538000
0L
#539000
0R
1\
#540000
1M
1W
0"
#542000
0I
0N
1H
1S
#544000
1L
#545000
b100110100001101 :
b100110100001101 J
0D
0Q
0G
0X
1"
#546000
1D
0M
0F
0]
#548000
0D
1I
1N
1R
#550000
0L
1V
0"
#551000
1D
0H
0S
#552000
1M
#553000
1[
#554000
0D
0I
0N
1Q
#555000
b1001101000011010 :
b1001101000011010 J
0W
1"
#556000
1L
#557000
0R
#558000
0M
#560000
1D
1I
1N
1H
1S
1G
1X
0"
0\
#562000
0L
#563000
0Q
#564000
1M
#565000
b11010000110101 :
b11010000110101 J
0V
1"
#566000
0D
0I
0N
1R
#567000
1D
1F
1]
#568000
1L
#569000
0D
0H
0S
#570000
0M
1W
0"
#572000
1D
1I
1N
1Q
#574000
0L
0[
#575000
b110100001101011 :
b110100001101011 J
0D
0R
0G
0X
1"
#576000
1M
#578000
0I
0N
1H
1S
#580000
1L
1V
0"
#581000
0Q
1\
#582000
0M
#584000
1D
1I
1N
1R
#585000
b1101000011010111 :
b1101000011010111 J
0W
1"
#586000
0L
#587000
0D
0H
0S
#588000
1D
1M
0F
0]
#590000
1D
0I
0N
1Q
1G
1X
0"
#592000
1L
#593000
0R
#594000
0M
#595000
b1010000110101111 :
b1010000110101111 J
0V
1"
1[
#596000
1I
1N
1H
1S
#598000
0L
#599000
0Q
#600000
1M
1W
0"
#602000
0D
0I
0N
1R
0\
#604000
1L
#605000
b100001101011110 :
b100001101011110 J
0D
0H
0S
0G
0X
1"
#606000
0M
#608000
1D
1I
1N
1Q
#609000
0D
1F
1]
#610000
0L
1V
0"
#611000
0R
#612000
1M
#614000
0I
0N
1H
1S
#615000
b1000011010111100 :
b1000011010111100 J
0W
1"
#616000
1L
0[
#617000
0Q
#618000
0M
#620000
0D
1I
1N
1R
1G
1X
0"
#622000
0L
#623000
1D
0H
0S
1\
#624000
1M
#625000
1.
b110101111001 :
b110101111001 J
0V
1"
#626000
0D
0I
0N
1Q
#628000
1L
#629000
0R
#630000
1D
0M
1W
0"
0F
0]
#632000
1I
1N
1H
1S
#634000
0L
#635000
0.
b1101011110011 :
b1101011110011 J
b11 !
b11 A
0D
0Q
0G
0X
1"
#636000
1M
#637000
1[
#638000
1D
0I
0N
1R
#640000
1L
1V
0"
#641000
0D
0H
0S
#642000
0M
#644000
1D
1I
1N
1Q
0\
#645000
b11010111100111 :
b11010111100111 J
0W
1"
#646000
0L
#647000
0R
#648000
1M
#650000
0D
0I
0N
1H
1S
1G
1X
0"
#651000
1D
1F
1]
#652000
1L
#653000
0Q
#654000
0M
#655000
b110101111001111 :
b110101111001111 J
0V
1"
#656000
0D
1I
1N
1R
#658000
0L
0[
#659000
1D
0H
0S
#660000
1M
1W
0"
#662000
0D
0I
0N
1Q
#664000
1L
#665000
b1101011110011110 :
b1101011110011110 J
1D
0R
0G
0X
1"
1\
#666000
0M
#668000
1I
1N
1H
1S
#670000
0L
1V
0"
#671000
0Q
#672000
0D
1M
0F
0]
#674000
1D
0I
0N
1R
#675000
b1010111100111101 :
b1010111100111101 J
0W
1"
#676000
1L
#677000
0D
0H
0S
#678000
0M
#679000
1[
#680000
0D
1I
1N
1Q
1G
1X
0"
#682000
0L
#683000
0R
#684000
1M
#685000
b101111001111010 :
b101111001111010 J
0V
1"
#686000
0I
0N
1H
1S
0\
#688000
1L
#689000
0Q
#690000
0M
1W
0"
#692000
1D
1I
1N
1R
#693000
0D
1F
1]
#694000
0L
#695000
b1011110011110100 :
b1011110011110100 J
0D
0H
0S
0G
0X
1"
#696000
1M
#698000
1D
0I
0N
1Q
#700000
1L
1V
0"
0[
#701000
0R
#702000
0M
#704000
1I
1N
1H
1S
#705000
b111100111101001 :
b111100111101001 J
0W
1"
#706000
0L
#707000
0Q
1\
#708000
1M
#710000
1D
0I
0N
1R
1G
1X
0"
#712000
1L
#713000
0D
0H
0S
#714000
1D
0M
0F
0]
#715000
b1111001111010011 :
b1111001111010011 J
0V
1"
#716000
0D
1I
1N
1Q
#718000
0L
#719000
0R
#720000
1M
1W
0"
#721000
1[
#722000
0I
0N
1H
1S
#724000
1L
#725000
b1110011110100110 :
b1110011110100110 J
1D
0Q
0G
0X
1"
#726000
0M
#728000
0D
1I
1N
1R
0\
#730000
0L
1V
0"
#731000
1D
0H
0S
#732000
1M
#734000
0D
0I
0N
1Q
#735000
b1100111101001101 :
b1100111101001101 J
1D
0W
1"
1F
1]
#736000
1L
#737000
0R
#738000
0M
#740000
0D
1I
1N
1H
1S
1G
1X
0"
#742000
0L
0[
#743000
0Q
#744000
1M
#745000
b1001111010011010 :
b1001111010011010 J
0V
1"
#746000
1D
0I
0N
1R
#748000
1L
#749000
0D
0H
0S
1\
#750000
0M
1W
0"
#752000
1D
1I
1N
1Q
#754000
0L
#755000
b11110100110101 :
b11110100110101 J
0D
0R
0G
0X
1"
#756000
1D
1M
0F
0]
#758000
0I
0N
1H
1S
#760000
1L
1V
0"
#761000
0Q
#762000
0M
#763000
1[
#764000
0D
1I
1N
1R
#765000
b111101001101010 :
b111101001101010 J
0W
1"
#766000
0L
#767000
1D
0H
0S
#768000
1M
#770000
1D
0I
0N
1Q
1G
1X
0"
0\
#772000
1L
#773000
0R
#774000
0M
#775000
b1111010011010101 :
b1111010011010101 J
0V
1"
#776000
1I
1N
1H
1S
#777000
0D
1F
1]
#778000
0L
#779000
0Q
#780000
1M
1W
0"
#782000
1D
0I
0N
1R
#784000
1L
0[
#785000
b1110100110101011 :
b1110100110101011 J
1D
0H
0S
0G
0X
1"
#786000
0M
#788000
0D
1I
1N
1Q
#790000
0L
1V
0"
#791000
0R
1\
#792000
1M
#794000
0I
0N
1H
1S
#795000
b1101001101010110 :
b1101001101010110 J
0W
1"
#796000
1L
#797000
0Q
#798000
1D
0M
0F
0]
#800000
1D
1I
1N
1R
1G
1X
0"
#802000
0L
#803000
0D
0H
0S
#804000
1M
#805000
b1010011010101100 :
b1010011010101100 J
0V
1"
1[
#806000
1D
0I
0N
1Q
#808000
1L
#809000
0R
#810000
0M
1W
0"
#812000
1I
1N
1H
1S
0\
#814000
0L
#815000
b100110101011001 :
b100110101011001 J
0D
0Q
0G
0X
1"
#816000
1M
#818000
1D
0I
0N
1R
#819000
0D
1F
1]
#820000
1L
1V
0"
#821000
1D
0H
0S
#822000
0M
#824000
0D
1I
1N
1Q
#825000
b1001101010110010 :
b1001101010110010 J
0W
1"
#826000
0L
0[
#827000
0R
#828000
1M
#830000
1D
0I
0N
1H
1S
1G
1X
0"
#832000
1L
#833000
0Q
1\
#834000
0M
#835000
b11010101100101 :
b11010101100101 J
0V
1"
#836000
0D
1I
1N
1R
#838000
0L
#839000
1D
0H
0S
#840000
0D
1M
1W
0"
0F
0]
#842000
1D
0I
0N
1Q
#844000
1L
#845000
b110101011001011 :
b110101011001011 J
0D
0R
0G
0X
1"
#846000
0M
#847000
1[
#848000
1I
1N
1H
1S
#850000
0L
1V
0"
#851000
0Q
#852000
1M
#854000
1D
0I
0N
1R
0\
#855000
b1101010110010111 :
b1101010110010111 J
0W
1"
#856000
1L
#857000
0D
0H
0S
#858000
0M
#860000
0D
1I
1N
1Q
1G
1X
0"
#861000
1D
1F
1]
#862000
0L
#863000
0R
#864000
1M
#865000
b1010101100101111 :
b1010101100101111 J
0V
1"
#866000
0I
0N
1H
1S
#868000
1L
0[
#869000
0Q
#870000
0M
1W
0"
#872000
0D
1I
1N
1R
#874000
0L
#875000
b101011001011110 :
b101011001011110 J
0D
0H
0S
0G
0X
1"
1\
#876000
1M
#878000
1D
0I
0N
1Q
#880000
1L
1V
0"
#881000
0R
#882000
0D
0M
0F
0]
#884000
1I
1N
1H
1S
#885000
b1010110010111100 :
b1010110010111100 J
0W
1"
#886000
0L
#887000
0Q
#888000
1M
#889000
1[
#890000
0D
0I
0N
1R
1G
1X
0"
#892000
1L
#893000
1D
0H
0S
#894000
0M
#895000
b101100101111001 :
b101100101111001 J
0V
1"
#896000
0D
1I
1N
1Q
0\
#898000
0L
#899000
0R
#900000
1M
1W
0"
#902000
0I
0N
1H
1S
#903000
1D
1F
1]
#904000
1L
#905000
b1011001011110011 :
b1011001011110011 J
0D
0Q
0G
0X
1"
#906000
0M
#908000
1D
1I
1N
1R
#910000
0L
1V
0"
0[
#911000
0D
0H
0S
#912000
1M
#914000
1D
0I
0N
1Q
#915000
b110010111100111 :
b110010111100111 J
0W
1"
#916000
1L
#917000
0R
1\
#918000
0M
#920000
0D
1I
1N
1H
1S
1G
1X
0"
#922000
0L
#923000
0Q
